{
  "phase_1_critical": {
    "title": "Критические исправления",
    "duration": "1-2 недели",
    "tasks": [
      "Исправить утечки памяти",
      "Добавить проверки return NULL после PyErr_SetString",
      "Исправить критические проблемы безопасности"
    ]
  },
  "phase_2_architecture": {
    "title": "Архитектурные улучшения",
    "duration": "2-3 недели",
    "tasks": [
      "Улучшить thread safety",
      "Рефакторинг сложных функций",
      "Оптимизация производительности",
      "Улучшение API консистентности"
    ]
  },
  "phase_3_quality": {
    "title": "Повышение качества",
    "duration": "1-2 недели",
    "tasks": [
      "Добавить unit тесты",
      "Улучшить документацию",
      "Добавить статический анализ",
      "Code review процесс"
    ]
  }
}